[
  {
    "session_id": "proc_039c87aed2ce",
    "command": "cd /tmp/turnstile-solver && python3 solver-server-v2.py --api-key 8010000000ccojr5nrbg516w5jvw1wu9 --port 8878 2>&1",
    "pid": 9656,
    "pid_scope": "host",
    "host_start_time": 182026,
    "cwd": "/tmp/turnstile-solver",
    "started_at": 1782796677.3955271,
    "task_id": "default",
    "session_key": "b01caa0f201e",
    "watcher_platform": "webui",
    "watcher_chat_id": "b01caa0f201e",
    "watcher_user_id": "",
    "watcher_user_name": "",
    "watcher_thread_id": "",
    "watcher_message_id": "",
    "watcher_interval": 5,
    "notify_on_complete": true,
    "watch_patterns": []
  },
  {
    "session_id": "proc_058e4df54aab",
    "command": "cd /tmp/turnstile-solver && python3 solver-server-v2.py --api-key 8010000000ccojr5nrbg516w5jvw1wu9 --port 8822 2>&1",
    "pid": 9669,
    "pid_scope": "host",
    "host_start_time": 182182,
    "cwd": "/tmp/turnstile-solver",
    "started_at": 1782796678.9565694,
    "task_id": "default",
    "session_key": "b01caa0f201e",
    "watcher_platform": "",
    "watcher_chat_id": "",
    "watcher_user_id": "",
    "watcher_user_name": "",
    "watcher_thread_id": "",
    "watcher_message_id": "",
    "watcher_interval": 0,
    "notify_on_complete": false,
    "watch_patterns": []
  }
]